automation/__init__.py
automation/tests.py
automation/utils.py
flask_automation-1.2.dist-info/LICENSE
flask_automation-1.2.dist-info/METADATA
flask_automation-1.2.dist-info/WHEEL
flask_automation-1.2.dist-info/top_level.txt
flask_automation-1.2.dist-info/RECORD
