Metadata-Version: 2.1
Name: flask-automation
Version: 1.2
Summary: Common functionality across the different Flask microservices of the UofC UIS
Home-page: https://gitlab.developers.cam.ac.uk/uis/devops/flask-automation
Author: University of Cambridge Information Services
Author-email: automation@uis.cam.ac.uk
License: MIT
Platform: UNKNOWN
Classifier: Development Status :: 5 - Production/Stable
Classifier: Environment :: Web Environment
Classifier: Framework :: Flask
Classifier: Intended Audience :: Developers
Classifier: License :: OSI Approved :: MIT License
Classifier: Operating System :: OS Independent
Classifier: Programming Language :: Python
License-File: LICENSE
Requires-Dist: flask
